codecontextor/__init__.py
codecontextor/main.py
codecontextor-1.1.1.dist-info/LICENSE
codecontextor-1.1.1.dist-info/METADATA
codecontextor-1.1.1.dist-info/WHEEL
codecontextor-1.1.1.dist-info/entry_points.txt
codecontextor-1.1.1.dist-info/top_level.txt
codecontextor-1.1.1.dist-info/RECORD
