Metadata-Version: 2.1
Name: codecontextor
Version: 1.1.1
Summary: DEPRECATED: Please use 'contextor' package instead
Author-email: Salih Ergüt <salih.ergut@gmail.com>
Classifier: Development Status :: 7 - Inactive
Classifier: Intended Audience :: Developers
Classifier: License :: OSI Approved :: MIT License
Classifier: Programming Language :: Python :: 3
Requires-Python: >=3.8
License-File: LICENSE
Requires-Dist: pathspec>=0.12.1
